MANIFEST.in
README.md
docs_requirements.txt
requirements.txt
setup.py
test_requirements.txt
autodiscovery/__init__.py
autodiscovery/cli.py
autodiscovery/config.py
autodiscovery/data_processors.py
autodiscovery/exceptions.py
autodiscovery/output.py
autodiscovery/cli_sessions/__init__.py
autodiscovery/cli_sessions/base.py
autodiscovery/cli_sessions/ssh.py
autodiscovery/cli_sessions/telnet.py
autodiscovery/commands/__init__.py
autodiscovery/commands/connect_ports.py
autodiscovery/commands/echo_connections_template.py
autodiscovery/commands/echo_report_template.py
autodiscovery/commands/echo_user_input_template.py
autodiscovery/commands/echo_vendors_config_template.py
autodiscovery/commands/run.py
autodiscovery/commands/run_from_report.py
autodiscovery/commands/update_vendors.py
autodiscovery/common/__init__.py
autodiscovery/common/consts.py
autodiscovery/common/cs_session_manager.py
autodiscovery/common/utils.py
autodiscovery/handlers/__init__.py
autodiscovery/handlers/base.py
autodiscovery/handlers/layer1.py
autodiscovery/handlers/networking.py
autodiscovery/handlers/pdu.py
autodiscovery/handlers/traffic_generator.py
autodiscovery/models/__init__.py
autodiscovery/models/input_data.py
autodiscovery/models/vendor.py
autodiscovery/parsers/__init__.py
autodiscovery/parsers/config_data_parsers.py
autodiscovery/parsers/input_data_parsers.py
autodiscovery/reports/__init__.py
autodiscovery/reports/base.py
autodiscovery/reports/console.py
autodiscovery/reports/excel.py
autodiscovery/reports/connections/__init__.py
autodiscovery/reports/connections/base.py
autodiscovery/reports/connections/console.py
autodiscovery/reports/connections/excel.py
autodiscovery/reports/discovery/__init__.py
autodiscovery/reports/discovery/base.py
autodiscovery/reports/discovery/console.py
autodiscovery/reports/discovery/excel.py
cloudshell_autodiscovery.egg-info/PKG-INFO
cloudshell_autodiscovery.egg-info/SOURCES.txt
cloudshell_autodiscovery.egg-info/dependency_links.txt
cloudshell_autodiscovery.egg-info/entry_points.txt
cloudshell_autodiscovery.egg-info/requires.txt
cloudshell_autodiscovery.egg-info/top_level.txt
data/vendor_enterprise_numbers.json
data/vendors_config.json
examples/user_input_example.yml
examples/vendors_config_example.json
json_schemes/input_data_schema.json
