Metadata-Version: 1.0
Name: cloudshell-autodiscovery
Version: 1.0.0
Summary: UNKNOWN
Home-page: UNKNOWN
Author: Quali
Author-email: anton.p@qualisystems.com
License: Apache Software License 2.0
Platform: UNKNOWN
